DESCRIPTION.rst
LICENSE.txt
README.rst
setup.py
evoalgos/__init__.py
evoalgos/algo.py
evoalgos/individual.py
evoalgos/performance.py
evoalgos/reproduction.py
evoalgos/selection.py
evoalgos/sorting.py
evoalgos.egg-info/PKG-INFO
evoalgos.egg-info/SOURCES.txt
evoalgos.egg-info/dependency_links.txt
evoalgos.egg-info/requires.txt
evoalgos.egg-info/top_level.txt